eyerec/__init__.py
eyerec/_eyerec.cp36-win_amd64.pyd
eyerec-0.0.0.data/data/include/eyerec/PuRe.hpp
eyerec-0.0.0.data/data/include/eyerec/PuReST.hpp
eyerec-0.0.0.data/data/include/eyerec/Pupil.hpp
eyerec-0.0.0.data/data/include/eyerec/PupilDetectionMethod.hpp
eyerec-0.0.0.data/data/include/eyerec/PupilTrackingMethod.hpp
eyerec-0.0.0.data/data/include/eyerec/Timestamp.hpp
eyerec-0.0.0.data/data/include/eyerec/TrackingByDetection.hpp
eyerec-0.0.0.data/data/lib/eyerec.lib
eyerec-0.0.0.data/data/lib/cmake/eyerec/eyerec-config-version.cmake
eyerec-0.0.0.data/data/lib/cmake/eyerec/eyerec-config.cmake
eyerec-0.0.0.data/data/lib/cmake/eyerec/eyerec-targets-release.cmake
eyerec-0.0.0.data/data/lib/cmake/eyerec/eyerec-targets.cmake
eyerec-0.0.0.dist-info/METADATA
eyerec-0.0.0.dist-info/WHEEL
eyerec-0.0.0.dist-info/top_level.txt
eyerec-0.0.0.dist-info/RECORD
