Metadata-Version: 2.1
Name: eyerec
Version: 0.0.0
Summary: UNKNOWN
Home-page: UNKNOWN
Author: Thiago C. Santini
Author-email: 
License: UNKNOWN
Project-URL: Code, https://github.com/tcsantini/eyerec-python
Platform: UNKNOWN
Classifier: Development Status :: 2 - Pre-Alpha
Classifier: Intended Audience :: Developers
Classifier: Intended Audience :: Science/Research
Classifier: Programming Language :: Python :: 3
Requires-Dist: numpy
